searchlights/__init__.py
searchlights/data/sls_fsaverage_lh_10mm_icoorder5_fsaverage-mask.npz
searchlights/data/sls_fsaverage_rh_10mm_icoorder5_fsaverage-mask.npz
searchlights/data/on1031_dijkstra/onavg-ico32_lh_20mm.npz
searchlights/data/on1031_dijkstra/onavg-ico32_rh_20mm.npz
searchlights-0.2.0.dist-info/LICENSE.txt
searchlights-0.2.0.dist-info/METADATA
searchlights-0.2.0.dist-info/WHEEL
searchlights-0.2.0.dist-info/top_level.txt
searchlights-0.2.0.dist-info/RECORD
