Metadata-Version: 2.1
Name: searchlights
Version: 0.2.0
Summary: A collection of pre-computed searchlights.
Home-page: https://feilong.github.io/searchlights/
Author: Ma Feilong
Author-email: mafeilong@gmail.com
Project-URL: Bug Tracker, https://github.com/feilong/searchlights/issues
Project-URL: Source Code, https://github.com/feilong/searchlights
Keywords: brain,surface,fmri,mvpa,searchlight,searchlight-analysis
Classifier: Programming Language :: Python :: 3 :: Only
Classifier: Programming Language :: Python :: 3.6
Classifier: Programming Language :: Python :: 3.7
Classifier: Programming Language :: Python :: 3.8
Classifier: Programming Language :: Python :: 3.9
Classifier: Programming Language :: Python :: 3.10
Requires-Python: >=3.6
License-File: LICENSE.txt
Requires-Dist: numpy
Requires-Dist: surface-spaces
Provides-Extra: extra
Requires-Dist: datalad ; extra == 'extra'
Provides-Extra: tests
Requires-Dist: pytest ; extra == 'tests'
